salat/__init__.py
salat/calculations.py
salat/methods.py
salat-1.1.0.dist-info/LICENSE
salat-1.1.0.dist-info/METADATA
salat-1.1.0.dist-info/WHEEL
salat-1.1.0.dist-info/top_level.txt
salat-1.1.0.dist-info/RECORD
