Metadata-Version: 2.1
Name: salat
Version: 1.1.0
Summary: Tool to calculate accurate salat (prayer) times
Home-page: https://github.com/zainhussaini/salat
Author: Zain Hussaini
Author-email: zih301@gmail.com
License: MIT
Classifier: License :: OSI Approved :: MIT License
Classifier: Programming Language :: Python :: 3
Classifier: Programming Language :: Python :: 3.6
License-File: LICENSE
